[
	{
		"id":"legal-service",
		"name":"Legal Services",
		"contact": "Contact Name 1",
		"snippet":"service No1",
		"imageUrl": "img/s01.png",
		"age": 1
	},{
		"id":"alliances-partnerships",
		"name": "Partnerships",
		"contact": "Contact Name 2",
		"snippet":"service No2",
		"imageUrl": "img/s02.png",
		"age": 2
	},{
		"id":"capital-investments",
		"name":"Capital Investments",
		"contact": "Contact Name 3",
		"snippet": "service No3",
		"imageUrl": "img/s03.png",
		"age": 3
	},{
		"id":"due-diligence",
		"name":"Due Diligence",
		"contact": "Contact Name 4",
		"snippet": "service No4",
		"imageUrl": "img/s04.jpg",
		"age": 4
	},{
		"id":"employement-agreements",
		"name":"Employment Agreements",
		"contact": "Contact Name 5",
		"snippet": "service No5",
		"imageUrl": "img/s05.png",
		"age": 5
	},{
		"id":"litigation-management",
		"name":"Litigation Management",
		"contact": "Contact Name 6",
		"snippet": "service No6",
		"imageUrl": "img/s06.png",
		"age": 6
	}
]